CHANGES.md
LICENSE.txt
MANIFEST.in
README.md
setup.py
lib/eol.py
lib/eol.egg-info/PKG-INFO
lib/eol.egg-info/SOURCES.txt
lib/eol.egg-info/dependency_links.txt
lib/eol.egg-info/entry_points.txt
lib/eol.egg-info/not-zip-safe
lib/eol.egg-info/top_level.txt
test/test.py
test/test_eol.py
test/testlib.py