Metadata-Version: 1.0
Name: eol
Version: 0.7.5
Summary: a command-line script and Python module for working with text file end-of-line (EOL) characters
Home-page: http://github.com/trentm/eol
Author: Trent Mick
Author-email: trentm@gmail.com
License: MIT
Keywords: eol cli cr crlf lf
Platform: UNKNOWN
Classifier: Development Status :: 5 - Production/Stable
Classifier: Environment :: Console
Classifier: Intended Audience :: Developers
Classifier: License :: OSI Approved :: MIT License
Classifier: Operating System :: OS Independent
Classifier: Programming Language :: Python :: 2
Classifier: Programming Language :: Python :: 2.4
Classifier: Programming Language :: Python :: 2.5
Classifier: Programming Language :: Python :: 2.6
Classifier: Programming Language :: Python :: 2.7
Classifier: Programming Language :: Python :: 3
Classifier: Programming Language :: Python :: 3.1
Classifier: Topic :: Software Development :: Libraries :: Python Modules
